nonholonomics/__init__.py
nonholonomics/NHL/NHL.py
nonholonomics/NHL/__init__.py
nonholonomics/Simulation/Simulation.py
nonholonomics/Simulation/__init__.py
nonholonomics-0.0.13.dist-info/AUTHORS
nonholonomics-0.0.13.dist-info/LICENSE
nonholonomics-0.0.13.dist-info/METADATA
nonholonomics-0.0.13.dist-info/WHEEL
nonholonomics-0.0.13.dist-info/top_level.txt
nonholonomics-0.0.13.dist-info/RECORD
